{
  "last_sync": "2026-03-23T16:32:46.600137",
  "files": {
    "/office/invoices/group inc.pdf": {
      "modified": "2026-03-23T19:29:50Z",
      "size": 1955003,
      "name": "GROUP INC.pdf",
      "synced_at": "2026-03-23T15:33:07.153212"
    },
    "/office/invoices/impact food distributing ine..pdf": {
      "modified": "2026-03-23T19:29:22Z",
      "size": 3960303,
      "name": "Impact Food Distributing Ine..pdf",
      "synced_at": "2026-03-23T15:33:25.064532"
    },
    "/office/invoices/dairy wagon_mwf1-049580_03-02-2026.pdf": {
      "modified": "2026-03-05T13:58:26Z",
      "size": 1754599,
      "name": "Dairy Wagon_MWF1-049580_03-02-2026.pdf",
      "synced_at": "2026-03-23T15:33:44.080670"
    },
    "/office/invoices/wheatfield_1748772_03-03-2026.pdf": {
      "modified": "2026-03-04T14:34:09Z",
      "size": 3294261,
      "name": "WHEATFIELD_1748772_03-03-2026.pdf",
      "synced_at": "2026-03-23T15:34:07.696380"
    },
    "/office/invoices/wheatfield_1747985_02-27-2026.pdf": {
      "modified": "2026-03-04T02:32:54Z",
      "size": 2004422,
      "name": "WHEATFIELD_1747985_02-27-2026.pdf",
      "synced_at": "2026-03-23T15:34:31.233612"
    },
    "/office/invoices/unknown_020_2026-03-04.pdf": {
      "modified": "2026-03-02T20:27:55Z",
      "size": 3151432,
      "name": "Unknown_020_2026-03-04.pdf",
      "synced_at": "2026-03-23T15:34:46.396414"
    },
    "/office/invoices/whitestone,_11357_2026-03-04.pdf": {
      "modified": "2026-03-02T14:45:53Z",
      "size": 2171567,
      "name": "Whitestone,_11357_2026-03-04.pdf",
      "synced_at": "2026-03-23T15:35:09.826678"
    },
    "/office/invoices/street_1016_2026-03-04.pdf": {
      "modified": "2026-03-02T14:45:28Z",
      "size": 1955747,
      "name": "Street_1016_2026-03-04.pdf",
      "synced_at": "2026-03-23T15:35:34.181801"
    },
    "/office/invoices/invoice_2516_01-07-2026.pdf": {
      "modified": "2026-03-02T14:44:47Z",
      "size": 3305032,
      "name": "INVOICE_2516_01-07-2026.pdf",
      "synced_at": "2026-03-23T15:35:48.615233"
    },
    "/office/invoices/redway_2048879_12-6-2025.pdf": {
      "modified": "2026-03-02T14:43:34Z",
      "size": 3415492,
      "name": "REDWAY_2048879_12-6-2025.pdf",
      "synced_at": "2026-03-23T15:36:07.593510"
    },
    "/office/invoices/invoice_1270_11-24-25.pdf": {
      "modified": "2026-03-02T14:43:06Z",
      "size": 4129650,
      "name": "Invoice_1270_11-24-25.pdf",
      "synced_at": "2026-03-23T15:36:25.863102"
    },
    "/office/invoices/invoice_2507_01-05-2026.pdf": {
      "modified": "2026-03-02T14:42:40Z",
      "size": 2231712,
      "name": "INVOICE_2507_01-05-2026.pdf",
      "synced_at": "2026-03-23T15:36:37.181847"
    },
    "/office/invoices/orporated_724_2026-03-04.pdf": {
      "modified": "2026-03-02T14:41:04Z",
      "size": 6682336,
      "name": "ORPORATED_724_2026-03-04.pdf",
      "synced_at": "2026-03-23T15:37:12.717558"
    },
    "/office/invoices/w.jefryn_11729_02-19-26.pdf": {
      "modified": "2026-03-02T14:38:48Z",
      "size": 3059238,
      "name": "W.Jefryn_11729_02-19-26.pdf",
      "synced_at": "2026-03-23T15:37:32.848241"
    },
    "/office/invoices/smee_020_2026-03-04.pdf": {
      "modified": "2026-03-02T14:37:45Z",
      "size": 3822736,
      "name": "Smee_020_2026-03-04.pdf",
      "synced_at": "2026-03-23T15:37:47.249459"
    },
    "/office/invoices/lmpact_07206_1-12-2026.pdf": {
      "modified": "2026-03-02T14:36:36Z",
      "size": 3192332,
      "name": "lmpact_07206_1-12-2026.pdf",
      "synced_at": "2026-03-23T15:38:03.103875"
    },
    "/office/invoices/unknown_xxxx_2026-03-04.pdf": {
      "modified": "2026-03-02T14:36:19Z",
      "size": 3718690,
      "name": "Unknown_XXXX_2026-03-04.pdf",
      "synced_at": "2026-03-23T15:38:17.860689"
    },
    "/office/invoices/w.jefryn_11729_02-26-26.pdf": {
      "modified": "2026-03-02T14:32:08Z",
      "size": 3320953,
      "name": "W.Jefryn_11729_02-26-26.pdf",
      "synced_at": "2026-03-23T15:38:37.643549"
    },
    "/office/invoices/odeko_247_02-25-202.pdf": {
      "modified": "2026-03-02T14:31:34Z",
      "size": 3173463,
      "name": "Odeko_247_02-25-202.pdf",
      "synced_at": "2026-03-23T15:38:57.077263"
    },
    "/office/invoices/loumidis_1270_2-25-2026.pdf": {
      "modified": "2026-03-02T14:30:36Z",
      "size": 3460893,
      "name": "LOUMIDIS_1270_2-25-2026.pdf",
      "synced_at": "2026-03-23T15:39:18.311766"
    },
    "/office/invoices/redway/invoice_2065744_2-2-2026.pdf": {
      "modified": "2026-02-04T00:37:04Z",
      "size": 4222061,
      "name": "INVOICE_2065744_2-2-2026.pdf",
      "synced_at": "2026-03-23T15:39:43.971497"
    },
    "/office/invoices/impact foods/roas_xxxx_2026-03-04.pdf": {
      "modified": "2026-01-30T23:01:08Z",
      "size": 5217849,
      "name": "ROAS_XXXX_2026-03-04.pdf",
      "synced_at": "2026-03-23T15:39:59.614821"
    },
    "/office/invoices/loumidis/bremiun_957_1-15-2026.pdf": {
      "modified": "2026-01-30T23:00:43Z",
      "size": 4930392,
      "name": "BREMIUN_957_1-15-2026.pdf",
      "synced_at": "2026-03-23T15:40:18.858848"
    },
    "/office/invoices/impact foods/unknown_xxxx_2026-03-04.pdf": {
      "modified": "2026-01-30T23:00:08Z",
      "size": 6179082,
      "name": "Unknown_XXXX_2026-03-04.pdf",
      "synced_at": "2026-03-23T15:40:33.857415"
    },
    "/office/invoices/optima/opti_692439_01-15-26.pdf": {
      "modified": "2026-01-30T22:59:03Z",
      "size": 5611970,
      "name": "opti_692439_01-15-26.pdf",
      "synced_at": "2026-03-23T15:40:58.799653"
    },
    "/office/invoices/untitled folder 3/invoice_2563_01-22-2026.pdf": {
      "modified": "2026-01-30T22:52:11Z",
      "size": 3537635,
      "name": "INVOICE_2563_01-22-2026.pdf",
      "synced_at": "2026-03-23T15:41:15.585000"
    },
    "/office/invoices/optima/w.jefryn_11729_01-23-26.pdf": {
      "modified": "2026-01-30T22:51:17Z",
      "size": 3505614,
      "name": "W.Jefryn_11729_01-23-26.pdf",
      "synced_at": "2026-03-23T15:41:38.711439"
    },
    "/office/invoices/untitled folder 2/dairy_11370_1-29-26.pdf": {
      "modified": "2026-01-30T22:50:40Z",
      "size": 1375886,
      "name": "Dairy_11370_1-29-26.pdf",
      "synced_at": "2026-03-23T15:41:52.481829"
    },
    "/office/invoices/untitled folder/street_1016_2026-03-04.pdf": {
      "modified": "2026-01-30T22:49:41Z",
      "size": 2755886,
      "name": "Street_1016_2026-03-04.pdf",
      "synced_at": "2026-03-23T15:42:10.097719"
    },
    "/office/invoices/redway/invoice_2044957_11-20-2025.pdf": {
      "modified": "2026-01-30T22:48:58Z",
      "size": 4484089,
      "name": "INVOICE_2044957_11-20-2025.pdf",
      "synced_at": "2026-03-23T15:42:30.957119"
    },
    "/office/invoices/optima/tiene_1172_01-08-26.pdf": {
      "modified": "2026-01-30T22:46:53Z",
      "size": 4037509,
      "name": "tiene_1172_01-08-26.pdf",
      "synced_at": "2026-03-23T15:42:51.318766"
    }
  },
  "last_summary": {
    "new_files": 0,
    "updated_files": 0,
    "skipped_files": 31,
    "failed_files": 0,
    "review_required": 0,
    "last_sync": "2026-03-23T16:32:46.600137"
  }
}